x11util/__init__.py
x11util-1.3.dist-info/LICENSE
x11util-1.3.dist-info/METADATA
x11util-1.3.dist-info/WHEEL
x11util-1.3.dist-info/top_level.txt
x11util-1.3.dist-info/RECORD
