Metadata-Version: 2.1
Name: x11util
Version: 1.3
Summary: Wrapper fucntions to make X11 low-level Xlib programming easier
Home-page: https://github.com/h-ohsaki/x11util.git
Author: Hiroyuki Ohsaki
Author-email: ohsaki@lsnl.jp
License: UNKNOWN
Platform: UNKNOWN
Classifier: Programming Language :: Python :: 3
Classifier: License :: OSI Approved :: GNU General Public License v3 or later (GPLv3+)
Classifier: Operating System :: POSIX
Requires-Dist: Xlib
